mailify_md/CONSTANTS.py
mailify_md/__init__.py
mailify_md/__main__.py
mailify_md/cli.py
mailify_md/mailify_md.py
mailify_md/utils.py
mailify_md/data/dark_style_bak.css
mailify_md/data/light_style_bak.css
mailify_md/data/builtins/auto-render.min.js
mailify_md/data/builtins/base.js
mailify_md/data/builtins/katex.inlined.css
mailify_md/data/builtins/katex.min.js
mailify_md-0.1.5.dist-info/licenses/LICENSE
mailify_md-0.1.5.dist-info/METADATA
mailify_md-0.1.5.dist-info/WHEEL
mailify_md-0.1.5.dist-info/entry_points.txt
mailify_md-0.1.5.dist-info/top_level.txt
mailify_md-0.1.5.dist-info/RECORD
