Metadata-Version: 2.4
Name: mailify-md
Version: 0.1.5
Summary: 一个将 Markdown 文件转换为适合电子邮件的 HTML 的工具，并支持自定义 CSS 
Author: 2bitbit
License: MIT License
Project-URL: Homepage, https://github.com/2bitbit/mailify-md
Project-URL: Bug Tracker, https://github.com/2bitbit/mailify-md/issues
Keywords: markdown,email,html,converter,katex
Classifier: Programming Language :: Python :: 3
Classifier: License :: OSI Approved :: MIT License
Classifier: Operating System :: OS Independent
Classifier: Topic :: Text Processing :: Markup :: HTML
Classifier: Topic :: Utilities
Requires-Python: >=3.10
License-File: LICENSE
Requires-Dist: cairosvg
Requires-Dist: requests
Requires-Dist: premailer
Requires-Dist: Pygments
Requires-Dist: typer[all]
Requires-Dist: markdown-it-py[linkify,plugins]
Requires-Dist: beautifulsoup4
Requires-Dist: playwright
Dynamic: license-file
